.bumpversion.cfg
.cookiecutterrc
.editorconfig
.pre-commit-config.yaml
.readthedocs.yml
LICENSE
MANIFEST.in
README.md
pyproject.toml
setup.cfg
setup.py
src/logitech_flow_kvm/__init__.py
src/logitech_flow_kvm/__main__.py
src/logitech_flow_kvm/cli.py
src/logitech_flow_kvm/constants.py
src/logitech_flow_kvm/exceptions.py
src/logitech_flow_kvm/util.py
src/logitech_flow_kvm.egg-info/PKG-INFO
src/logitech_flow_kvm.egg-info/SOURCES.txt
src/logitech_flow_kvm.egg-info/dependency_links.txt
src/logitech_flow_kvm.egg-info/entry_points.txt
src/logitech_flow_kvm.egg-info/not-zip-safe
src/logitech_flow_kvm.egg-info/requires.txt
src/logitech_flow_kvm.egg-info/top_level.txt
src/logitech_flow_kvm/commands/__init__.py
src/logitech_flow_kvm/commands/flow_client.py
src/logitech_flow_kvm/commands/flow_server.py
src/logitech_flow_kvm/commands/list_devices.py
src/logitech_flow_kvm/commands/switch_to_host.py
src/logitech_flow_kvm/commands/watch.py
src/logitech_flow_kvm/tests/__init__.py