Metadata-Version: 2.1
Name: logitech-flow-kvm
Version: 1.1.0
Summary: Quickly switch between paired devices when using a mouse and keyboard that supports Logitech Flow.
Home-page: https://github.com/coddingtonbear/logitech-flow-kvm
Author: Adam Coddington
Author-email: me@adamcoddington.net
License: MIT
Project-URL: Documentation, https://logitech-flow-kvm.readthedocs.io/
Project-URL: Changelog, https://logitech-flow-kvm.readthedocs.io/en/latest/changelog.html
Project-URL: Issue Tracker, https://github.com/coddingtonbear/logitech-flow-kvm/issues
Platform: UNKNOWN
Classifier: Development Status :: 5 - Production/Stable
Classifier: Intended Audience :: Developers
Classifier: License :: OSI Approved :: MIT License
Classifier: Operating System :: Unix
Classifier: Operating System :: POSIX
Classifier: Operating System :: Microsoft :: Windows
Classifier: Programming Language :: Python
Classifier: Programming Language :: Python :: 3
Classifier: Programming Language :: Python :: 3 :: Only
Classifier: Programming Language :: Python :: 3.6
Classifier: Programming Language :: Python :: 3.7
Classifier: Programming Language :: Python :: 3.8
Classifier: Programming Language :: Python :: 3.9
Classifier: Programming Language :: Python :: Implementation :: CPython
Classifier: Programming Language :: Python :: Implementation :: PyPy
Classifier: Topic :: Utilities
Requires-Python: >=3.6
License-File: LICENSE
